wait_pid_wrapper.py
wait_pid_wrapper-0.1.0.dist-info/METADATA
wait_pid_wrapper-0.1.0.dist-info/WHEEL
wait_pid_wrapper-0.1.0.dist-info/entry_points.txt
wait_pid_wrapper-0.1.0.dist-info/RECORD
