Metadata-Version: 2.1
Name: wait-pid-wrapper
Version: 0.1.0
Summary: 
License: GPL-3.0
Author: Dick Marinus
Author-email: dick@mrns.nl
Requires-Python: >=3.12,<4.0
Classifier: License :: OSI Approved :: GNU General Public License v3 (GPLv3)
Classifier: Programming Language :: Python :: 3
Classifier: Programming Language :: Python :: 3.12
